ApplicationTracker/__init__.py
ApplicationTracker/main.py
GmailJobApplicationTracker-0.1.0.dist-info/METADATA
GmailJobApplicationTracker-0.1.0.dist-info/WHEEL
GmailJobApplicationTracker-0.1.0.dist-info/entry_points.txt
GmailJobApplicationTracker-0.1.0.dist-info/top_level.txt
GmailJobApplicationTracker-0.1.0.dist-info/RECORD
